cortex_common/__init__.py
cortex_common/constants/__init__.py
cortex_common/constants/contexts.py
cortex_common/constants/types.py
cortex_common/types/__init__.py
cortex_common/types/api.py
cortex_common/types/attribute_values.py
cortex_common/types/attributes.py
cortex_common/types/events.py
cortex_common/types/profiles.py
cortex_common/types/schemas.py
cortex_common/types/summaries.py
cortex_common/utils/__init__.py
cortex_common/utils/assertion_utils.py
cortex_common/utils/attr_utils.py
cortex_common/utils/class_utils.py
cortex_common/utils/config_utils.py
cortex_common/utils/dataframe_utils.py
cortex_common/utils/equality_utils.py
cortex_common/utils/etl_utils.py
cortex_common/utils/generator_utils.py
cortex_common/utils/id_utils.py
cortex_common/utils/object_utils.py
cortex_common/utils/string_utils.py
cortex_common/utils/time_utils.py
cortex_common/utils/type_utils.py
cortex_common/validators/__init__.py
cortex_common/validators/lists.py
cortex_profiles/__init__.py
cortex_profiles/build/__init__.py
cortex_profiles/build/attributes/__init__.py
cortex_profiles/build/attributes/builders.py
cortex_profiles/build/attributes/from_declarations.py
cortex_profiles/build/attributes/from_app_interactions/__init__.py
cortex_profiles/build/attributes/from_app_interactions/for_app_users.py
cortex_profiles/build/attributes/from_insight_interactions/__init__.py
cortex_profiles/build/attributes/from_insight_interactions/attribute_building_utils.py
cortex_profiles/build/attributes/from_insight_interactions/etl_utils.py
cortex_profiles/build/attributes/from_insight_interactions/for_insight_consumers.py
cortex_profiles/build/attributes/from_insights/__init__.py
cortex_profiles/build/attributes/from_insights/for_tagged_entities.py
cortex_profiles/build/attributes/from_sessions/__init__.py
cortex_profiles/build/attributes/from_sessions/attribute_building_utils.py
cortex_profiles/build/attributes/from_sessions/etl_utils.py
cortex_python_profiles-1.2.1.dist-info/LICENSE
cortex_python_profiles-1.2.1.dist-info/METADATA
cortex_python_profiles-1.2.1.dist-info/WHEEL
cortex_python_profiles-1.2.1.dist-info/top_level.txt
cortex_python_profiles-1.2.1.dist-info/RECORD
