Metadata-Version: 2.1
Name: cortex-python-profiles
Version: 1.2.1
Summary: Profile of 1 Extension for the Base Python Module of the Cortex Cognitive Platform
Home-page: https://github.com/CognitiveScale/cortex-python-profiles
Author: CognitiveScale
Author-email: info@cognitivescale.com
License: Apache License Version 2.0
Platform: linux
Platform: osx
Classifier: Operating System :: MacOS :: MacOS X
Classifier: Operating System :: POSIX
Classifier: Programming Language :: Python :: 3.6
Requires-Dist: cortex-python[builders] (<2.0,>=1.4.0)
Requires-Dist: pydash (<4.8,>=4.7.3)
Requires-Dist: arrow (<0.13,>=0.12.1)
Requires-Dist: pandas (>=0.23.4)
Requires-Dist: attrs (==18.2.0)
Requires-Dist: objectpath (==0.6.1)
Requires-Dist: deprecation (==2.0.6)
Provides-Extra: bulk
Requires-Dist: pymongo (<3.11,>=3.10.1) ; extra == 'bulk'
Provides-Extra: dev
Requires-Dist: twine (<2,>=1.12.1) ; extra == 'dev'
Requires-Dist: setuptools ; extra == 'dev'
Requires-Dist: wheel ; extra == 'dev'
Requires-Dist: pipdeptree ; extra == 'dev'
Requires-Dist: mypy (==0.770) ; extra == 'dev'
Requires-Dist: pylint (<3,>=2.3.0) ; extra == 'dev'
Provides-Extra: docs
Requires-Dist: Sphinx (<3,>=2) ; extra == 'docs'
Requires-Dist: sphinx-multiversion (==0.2.4) ; extra == 'docs'
Requires-Dist: gitpython (==3.1.7) ; extra == 'docs'
Requires-Dist: sphinx-rtd-theme (==0.5.0) ; extra == 'docs'
Requires-Dist: sphinxcontrib-restbuilder (==0.2) ; extra == 'docs'
Requires-Dist: nbconvert (==5.4.0) ; extra == 'docs'
Provides-Extra: synthetic
Requires-Dist: iso3166 (==1.0) ; extra == 'synthetic'
Requires-Dist: Faker (==2.0.0) ; extra == 'synthetic'
Provides-Extra: test
Requires-Dist: mocket (<3,>=2.5.0) ; extra == 'test'
Requires-Dist: mock (<3,>=2) ; extra == 'test'
Requires-Dist: pipdeptree ; extra == 'test'
Requires-Dist: tox (<3,>=2.9.1) ; extra == 'test'
Requires-Dist: pytest-cov (==2.5.1) ; extra == 'test'
Requires-Dist: pytest (<4,>=3.2.5) ; extra == 'test'
Provides-Extra: viz
Requires-Dist: cortex-python[jupyter] (<2.0,>=1.4.0) ; extra == 'viz'
Requires-Dist: psutil ; extra == 'viz'
